{
	"details":{
		"name":"kundana",
		"image":"images.png",
		"phone":"9876543210",
		"email":"kundanaballa99@gmail.com"
	},
	"education":[
		{
			"course":"B.Tech(CSE)",
			"college":"Mic college",
			"percentage":"81%"
		},
		{
			"course":"intermediate(MPC)",
			"college":"Sri Chaitanya jr college",
			"percentage":"92%"
		},
		{
			"course":"SSC",
			"college":"Noble kids high school",
			"percentage":"95%"
		}
	],
	"skills":[
		{
			"title":"programming Languages",
			"output":[
				"C","C++","Java","Python"
			]
		},
		{
			"title":"Operating systems",
			"output":[
			   "Windows","Linux","MAC"
			]
		}
	],
	"career":{
		"text":"to associate with organisation and utilize by technical skills"
	}
}